v_crypt/__init__.py
v_crypt/defaults.py
v_crypt/encryption.py
v_crypt/utilities.py
v_crypt/v_crypt.py
v_crypt-1.0.4.dist-info/LICENSE.txt
v_crypt-1.0.4.dist-info/METADATA
v_crypt-1.0.4.dist-info/WHEEL
v_crypt-1.0.4.dist-info/top_level.txt
v_crypt-1.0.4.dist-info/RECORD
