Metadata-Version: 2.1
Name: v-crypt
Version: 1.0.4
Summary: Utility to easily store password/secrets.
Home-page: https://github.com/villoro/v-crypt
Author: Arnau Villoro
Author-email: arnau@villoro.com
License: MIT
Platform: UNKNOWN
Classifier: Intended Audience :: Developers
Classifier: Intended Audience :: Education
Classifier: Intended Audience :: Manufacturing
Classifier: Intended Audience :: Science/Research
Classifier: License :: OSI Approved :: MIT License
Classifier: Programming Language :: Python
Classifier: Programming Language :: Python :: 3.6
Requires-Dist: cryptography (>=2.3)
